[{"run_id": 1742383245000, "name": "", "distance": 2047.08, "moving_time": "0:13:34.550000", "type": "Run", "subtype": "", "start_date": "2025-03-19 11:20:45", "start_date_local": "2025-03-19 19:20:45", "location_country": "\u73af\u6e56\u8def, \u5929\u9876\u8857\u9053, \u957f\u6c99\u5e02, \u6e58\u6c5f\u65b0\u533a, \u5cb3\u9e93\u533a, \u957f\u6c99\u5e02, \u6e56\u5357\u7701, 410205, \u4e2d\u56fd", "summary_polyline": "ypbkDcmbpTAAACAA?EACACAE?EAE?E?E?E?E@G?E?C?E?C?E?C?C?E?E?E@GAE?E?G?E?G?EAG?GAEAGAGAEAEAEAEAEAEAEACAEAEACAEACAEAEACAE?CAE?CAE?E?C?E?E?C?E?E?E?EAC?EAEACAEACAEACACAEAEAC?EAC?EAE?E?C?EAE?E?C?EACACCCACCCECCACCEACAE?CAE?CAEACAEACACACACCEACACCCACACACCCACACCCACCCACCCACCCAACCCCACCACCCACCCAECCACCCCCAECCAEACCC?EAC?C?EAE?C?E?E?C?E?EAC?E?CAE?CACAE?CAE?CAE?CAC?EAC?CAE?CAE?C?CAE?EAC?E?EAC?E?C?E?C?E?C?E?C?E@E?C@E?E@C?E@E?C@E@C@E@C@C@E@C@E@C@C@E@C@E?C@E?C@E@C@E?C@E?C?E@C?E?E?CAE?E?C?E?E?E?CAE?E?E?E?C?EAE?CAE?EACAEAEACAEACAEACACACAECCAEAEACAEAEAC?EAE?CAE?E?C?E?E?E?E?CAE?EAEAC?EAE?CAEAE?CACAECCACAECCACACAE?C@A@CBADABADAB?DAB?DAB?DABABAB?BABADAB?BABABAD?BAB?BAD?BAB?B?D?B?BAB?D?B?BAB?DAB?BAB?BADABABABADABABAD?BADABAB?D?BAD?BAB?DAB?DAB?D?BAD?BAD?BAD?BADAB?BCDABABABABADABABABABABCBABCBABABABCDABABABADABABADABABAD?BAB?B?BAB?D?B?D@B?B?D?B?B@B@D@B@BB@@BBBBBBB@B@D@B@B@B@B?B@B@D@@@BBBBBD@B@BBD@B@BBB@B@BBB@B@BBD@B@B@D@D@B@D@DBB@B@DB@@B@BBB@@@BBB@B@B?B@B?B@B?B@@?B@B?@@B?@@B?@?B?B?B?B?BAB?B?D?B@B?D@B?B@B?B?@?B?B?@?B?B?@?B?@?B?B@@?B@@?B@@@@?B@@@@?B@@?B@B@@?D@B?B?B?DABADABADCBABCBADABABAD?BAD?B?D?D?B?D?D?D?B?D?DAB?DADABADABABADABCBAD?DAB?D?D?BAD?D?B?DAD?BADAB?DAD?B?D?D?B?D?D?B@D?B@D?B@B?D@B?D?D?B@D?B?D@B?D@B?D@B@D?D@B?D?D?B?D@D?B?D?B@D@D@B?DBB@D@B@D@B@B@BBB@B@BBB@D@D@B@D@D?D@D?D?D?B?D?B?D?B?D@B?D@B@B@D@B@B@B@@@B@@@@@@@@@@@@?@@@@B@@@@@@@@?B@@@B?B@B?B?D?D?B?DAD?B?D?BAD@B@B@B@BB@@BBB@@BBBB@B@B@B@B?D@B?D?D?D?D?B?D?B@D?B?B@D@B@B@DB@BBB@B@B@@@B@@@@@@B?D@B?D@D?D?D?D?D?B?D?D@B@D@B@D@B@B@DBB@D@B@BBB@BBBBB@B@B@B@@BB@@@B@BBB@B@B@B@BBB@B@B@B@B@BBB@B@BBB@BBB@B@BBB@B@B@B@DBB@B@B@BBB@B@D@B@D@B@D?D@B@D@B?B@B@D?@@B?@@B?@@B?@@@?@@B?@@@?@?BA@A@A@A@A@A@ADAB", "average_heartrate": 140.0, "average_speed": 2.513, "streak": 1}, {"run_id": 1742470207000, "name": "", "distance": 3018.55, "moving_time": "0:20:26.750000", "type": "Run", "subtype": "", "start_date": "2025-03-20 11:30:07", "start_date_local": "2025-03-20 19:30:07", "location_country": "\u671b\u57ce\u5761\u8857\u9053, \u957f\u6c99\u5e02, \u6e58\u6c5f\u65b0\u533a, \u5cb3\u9e93\u533a, \u957f\u6c99\u5e02, \u6e56\u5357\u7701, 410205, \u4e2d\u56fd", "summary_polyline": "iqbkDwrbpTAA?AACACAC?AAC?AACAA?CAA?CAA?CAC?CAC?EACACAEAC?EAEACAE?CAEAEACAEAEAGAE?E?E?EAE?E?GAEAE?CAE?CACAEAEACACAE?EAC?E?E?EAE?E?E?EAEACCCAECAACCCCAECCAEACAE?CAEAC?CAE?CACACACACAECCACCCACCEACCCCCACCCACCAACCCACCCACCAACCCACCAACCCCACACACACAEACACAEACAEACAE?CAEAC?EAC?E?E?C?E?C?E?CAC?E?CAE?CACAC?CAE?CAC?CAE?CAEAC?CAC?CAE?C?CAE?C?EAC?E?C?C?E?C?E?C@C?E?C@E?C@E?C@E@C@E@C@C@C@C@C@E@C@C@E@C?C@C@C?C@E?C@C@C?E@C?E@C?C?E@C?E@C?C?E?C?C?C?C@C?E?C?C?C?E?C?C?C?CAE?C?C?C?EAC?E?CACAC?EACAAACACACACACACACACACACAC?CACACACAC?CAC?EACAC?E?CAC?E?C?EAE?C?EAE?C?EAC?EACAC?E?CAEACAC?EACACACAEAACC?CAC?C?A@ABABABAD?BAB?DABAB?BABADAB?BABAD?BABAB?BABAB?BAB?BAD?BABAB?BAD?BAB?B?B?D?B?B?BAB?BAB?BABABAB?BABABAD?BABABAB?BABAB?BAB?BAB?BAB?B?B?BAB?BAB?B?DAB?BAB?B?BABAB?BABABAB?BABABABABABABA@ABABABABABABABABABABABABABADABABABABABABA@ABAB?BAB?B?B?B?D?B?B?B?D?B@B?B?B@B@D@BBB@@BBB@@BB@@B@B@B@B@B?@@B?B?B@B@B@BB@@BD@B@B@B@DBB@B@BB@@BBB@BB@@B@D@B@B@D@B@B@DBB@B@D@B@BBB@BBB@B@B@BBB@B?D@B@D?B@B@D@B@B?D@B?D?BAD?B?DAB?D?B@B?D@B@D?B?D@B?D?B?D?B?D@B?BBD@B@B@B@B@B@B@D?B?B?DABABABCBADABCBABABADABAD?B?D?BAB?D?B?B?D?B?B?D?B?B?DAB?BADABABABABABCBADAD?BAD?B?D?B?D?B?BAD?B?DAB?BAD?BAD?DAB?D?B?D?B?B@D?B@B?D@B?D?B?D?B?D?B?D?B@D?B?D@B@B@D@B?B@D?B?D@B?D?D?B?B@D?B@D?B@B?D@B@D@B@B@B@DBB@B@@BB@B@B@D@B@B@D@D?B@D?B?D?B@D?B?D?B?B?D@B?B@B@B@D?B@B@B@B@BBB@B@@BBBB@@@BBB@B@B@B@D?B?B?B?D?D?BAD?D?B?D@B?D@B@DB@@B@BBB@@BB@BB@@B@B@D@B@D?D?B?DAD?BAD?B?B?B?D@B@B@B@BB@BBB@B@BB@@B@@@BB@@@B@D@B@D@DBB@D?B@B?B?B?BAB?B?D@B?B@D@B@D@DBD@B@D@BB@@B@BB@@B@BBB@B@B@B@B@BBB@B@BBB@B@D@BBB@BBB@B@B@BBB@B@BBB@B@B@DBB@B@B@D@B@B@BBD@B@B@D@B@B@D@B@B@D?B@D@B?B@D@B?D@B@D?D?BABABCBABABAB?B?B@D@B@B@B@BBB@B@B@D@B@B@B@@BB@@BB@BBB@B@D@B@B@D@B@B@B@B@D@B@B@D@BBB@B@B@B@BBD@@@BB?B@B?BABAB?D?B?BB@@@B@D@B@D@D@B@D@B@@@BB?@AB?BAD@B@@BBD@D?D@B?D@D@B@D?D@B@D?D@B@D?B@D@D@D@B?D@D@B@D?D@B?D@D?D@B@D?B@D@D@B@D@B@D@B@BBD@B@BBD@B@B?D@B@D?B@D@B?B?BCBABABCBABABAD?B?D?B?D@B?B?D?B?BCBCBC@CBC@CBABABAB?B@D?B@B@DBB@D@B@D@D@BBD@B@B@B@B@B@B@B@B@D@B@BBB@B@BBBB@@@B?D@BABABABABABAB?B?B?B@BBBBBBBB@BBD@B@B@D@B?B@D@D?B@D@B?D@D@B@D@D@B@DBB@B@BBD@B@B@DBB@B@BBB@B@B@D@B@B@B@B@D@B@B@B@B@D@B@B@B@BBD@B@B@B@B@DBB@B@B@D@BBB@B@B@BABADC@CBCBE@C@E@CBC@CBA@?B?B@D@B@B@BBD@B@B@B@B@D@B@BBD@BBB@B@B@B@B@D@B@D@B@B@D@B@BBB@D@BBB@DBB@B@BBB@B@DB@@BB@BBB@B@B?B@B?B?B?@?B?BA@?BABAB?BABABADABCBABABAB@B?@BBBBB@D@BBD@B@D@B@B@D@B@B@DBB@D@B@B@B@BBB@@B?@@DABABCBABCBCBABAD?BABBB@@BBD@B@D@D@B@B@D@BBB@B@B@B@B?D@B@B@B@B@D@B@B@DBB@B@B@D@B@B@D?D?BAD?D?DAB@D?B@DBB@BBB@D@BBB@B@@@B@@?B@?@@AA", "average_heartrate": 182.0, "average_speed": 2.461, "streak": 2}, {"run_id": 1742557460000, "name": "", "distance": 5202.99, "moving_time": "0:36:33.280000", "type": "Run", "subtype": "", "start_date": "2025-03-21 11:44:20", "start_date_local": "2025-03-21 19:44:20", "location_country": "\u671b\u57ce\u5761\u8857\u9053, \u957f\u6c99\u5e02, \u6e58\u6c5f\u65b0\u533a, \u5cb3\u9e93\u533a, \u957f\u6c99\u5e02, \u6e56\u5357\u7701, 410205, \u4e2d\u56fd", "summary_polyline": "m`ckDkobpT?D?@@B@?B@@A@?B?@?@AB?BA@?BABAB?BAB?BAB?D?B?BAB?BAB?BAD?B?BABABAB?DABABABABADABABABABAD?B?BAB?BAD?BAD?BABADABABAD?BAB?BAB?DAB?B?DAB?BAD?BAB?BAB?D?BAB?@ABABABAB?BABAB?B?BAB?B?DAB?B?BAB?DADADAFA^I@???@?@@B?@@B@@@BB@@B@@@B@@@@@B?@A@A@E?E?EAE?EAE?CAE?E?CAE?CAE?CACACACACAEACACCCACAE?CACACAEAC?CAEACAE?EAE?E?E?E?E?C?E?E?C?C?EAC?CACAC?CAEACACAEACAC?E?CAE?C?E?C?E?C?E?C?CACACACACACAACACACACAC?CAC?CACACAC?CACACACACAC?CACACAAACACCCACACACACAEACAACCACACCCCCACCAACCCACCAACCCAAACCAAACACCCACACCCAEAC?CAE?CAE?CAC?C?E?CAC?C?AAEAC?C?C?E?C?C?EAC?CAC?EAC?CAEAC?CACAE?CAC?E?C?CAE?C?EACAC?CAC?EAC?E?C?E?C?CAC?C?C?E?C@C?C?C?E@C?E@C@C@C@C@C@C@A@C@E@C?C@C@C?C@C@C@C?C@E?C@C@C?C?C@E?C@C?C@C?C?C@C?C?C?C?E?C?C?E?C?E?C?C?C?EAC?E?C?C?E?C?CAE?C?C?CAC?CACAC?CACACCCACACACACACACACACACACACAEAC?CAC?CAE?CAE?C?E?C?E@C?E?C?E?C?EAC?EACAC?CACAC?CACAC?CACACACACACCCACACAAACAE@C?CBABABADAB?BAD?B?BAB?B?BAB?DAB?BABAB?BAB?BAB?BAB?BAB?BAB?BABAB?B?BAB?B?BAB?BAB?B?B?B?BA@?BAB?BABAB?DABABABABABABAB?BAB?BAD?BAB?D?BAB?DAB?B?DAB?BAB?D?BAB?B?BAB?BAB?BABABABABABABABABABABABADABABABABABCBABABABCBABABABADAB?BABABABAB?BAB?B?B?B?B?B@B?BAB?D?B?B@B?B@B@BB@@BBB@@BB@BBB@B@B@B@B@B?B@B@B?B@@BB@@B@DBB@B@D@BBB@B@BBB@BBB@BBB@B@B@B@D@B@D@B@B@B@B@B@BB@@B@@BB@B@B@B@B@D@B@B@B?B@B?B@B@B?D@B?B?D?B?D?BAD?B?D?B?B@B@B?B@B@D?B?D@B?B?D?B@B?D@B@B?BBB@B@B@B?B@D?B?B?DABADABABABCBABABABABAB?BADAB?B?DAB?D?B?B?D?B@B?B?D?B?B?DABABADABABADABABABABABADABABAD?B?B?D?B?D?B?BAD?B?BAB?BADAB?DAB?B?B?D?B@B?B@B@B?D@B?B?B@D?B?B?DAB?D@B?B?D?B@D@B?B@B@D?B@D?B@B@D?B@B?B@D?B?D@D?B@B@D?B@B@B?B@B@BBB@B@B@BBB@B@B@B@D?B?B@B?B?B?D?B?B@D?B@D?B@D@B?D@D@B@D@B@B@B@B@BBB@B@BBB@B@B@B@B@BBB?B@B@D@B?B?D?D?D?B?D?D?D?B?B@D@BBB@BBB@@BB@B@BBB?B@D?B?D?B?DAB?D?B?B?D@B?D?D@B@D@@BB@@BB@?B@@?B@@@@?@B?@@@?B?BABAB?BA@?BAB?B?@AB@@?B@B@B?B@B@D@D@D?D@D@F@D@B@D@BBB@@BB@@BB@@@BB@@@@B@@BB@@BB@@B@@B@@BB@BB@@B@B@@BB@B@@@B@B@@BB@B@B@BB@@B@BBB@B@B@B@B@BBB@D@B@D@B@D@D@B?D@B@D?B@D?B@B@B@B@B@B@D@B@B@B?B?BA@ABABABABAB?B?@?B@B@B?B@B@B@BBB@D@B@B@BB@@BBBBB@B@@BB@B@B@B@D@B@B@D@BBB@B@D@B@B@D@B@B@D@B@B@B@B@BB@B@B?B@D?BBB@@B@D@B@B@D?B@B@BB@BB@?B?B?BABABAB?BAB@@B@B@B?D@D?B?D?B?D@B?D@B?B@D?B@B@B?D@B@D@B?B@D?B@B?B@B?D@B?B@D?B@B?B@B?D@B@B@B?B@B@@@B@B@B@D@B?B@D@B@D?B@B?B@B@D@B@B@D@B?D@B?DABA@ABABAB?B?B?B@B?B?D@B?B?DABABCBC@ABC@CBC@ABA@ABAB?B?B@B?B@B?B@B@D@B@BBB@D@BBB@D@BBB@B@BBD@B@B@B@D@BBB@@B@@@B?B?B?BAB?BAB?D?B?B?B@B@B@BB@BBB@D@B@B@BBD@B@BBB@B@D?B@D@B@D@B@D@B@B?DBB@B@BBB@B@B@B@B@D@BBB@B@B@B@BBD?B@D?B@B@B?DBB@B@B@B@D@BBB@D@B@B@D@D@B@D@B@B@D@B@B?D@B?B?BABCBA@CBC@A@C@C@C@?BA@?D@B@B@B@B@B@B@B@D@B@B@D@B@DBB@D@B@B@D@B@D@B@B@D@B@B@B@B@D@B@D@B@B@D@BBB@BBB@@B@BBB@B@@BB@B@B@D@B?B?B?B?DAB?DABABABCBABCBABCBABABABAB@B@BBBB@B@D@D@D@D?D@D?B@D@B@D@B@B@D?B@B@B@B@BBB@?B@BABABABABCDABCBABADAB@B?B@BB@@BBBBBB@B@BBB@B@B@B@B@B@B@B@B@B@B@B@B@D?B@B@B@B?B@D@B@B@B@D@B@B@B@B@D@B?B@BCBABABC@ABAB?B?B@B@B@B@B@D@B@B@B@B@B@B@D@B@B@B@B@D@B@B@B@B@D@B@B@@@B@BB@@BBB@B@BBB@B@B@D?B?BABABC@EBC@E@E@CBE@C@C@C@C@C@CBC@CBABABABAB?D?B?D?B?D@B?D@B?B@B@D@B@B?B@D@B?B@B?B@D?B?B@D?B?D?B?D?D?B?D?D?BAD?BAB?BADABABADABABABADABADAB?DAB?BAD?DAB?DAB?D?BAD?BAB?DAB?DAB?BAD?BAD?BABABADABCBABCBABABABABAB?BAD?B?B@D?B?B?D?B?B?D?B?D?D?B?D?D?D?B?D@B?B@D@B@B@B@BBB@@@BB@BBB?B?D@B?B?D?B?B?B?B?B?B?B?BAB?BABABADABABABAB?BABAB?BAB?BABA@ABABABABABA@ABABAB?BAB?B?B@B?D?B?D?D?B?D?BABAD?BABAB?DABABABABABABAB?BAB?B?B?B@D?B?B?D?BAB?B?BAD?B?BAB?BABABABAB?DABABA@?B?@@B@@?@@@?B?@AB?BABABABAB?DA@ABABABABCBABABA@ABCBABA@AB?B?B@B@B@B@B@BBB@@@BBB?B?B?BABABABABCBABA@ABABABABABABABABAB?DAB?B?D?B?B@@@B@B@BBB@@BB@BB@BB@@BBB@B@B@BBB?B@B@B@B@D?B@B?B@D?B@D?B@D@B@D@B@B@B@B@BBB@BBB@BB@@BB@BBB@B@B@BBB@B@B@B@B@B@B@B@B?D@B?B@B@B@B@B@B@B@B@B@B@B@B@B@B@D@B@B?D?B?D?B?B?B?B?B?B@B?D@B?B@B?D?B?B?BAB?BAB?@?@@?@@B?B?B?D?B@B?B@B@@@BBB@@BB@B@B@@?D?BAD?B@B?B@B@@B@@BB@@B@BBB@B@BBB@B@@BB@D@B?B?D?B?D@B?D?B?D@B@B@D@BBB@BBB@BBB@BB@B@B@B@B?B@B@B?B@B?B?B?BA@ABC@CBC@CBC@CBCBC@ABC@CBC@C@CBC@CBC@CBABC@ABAB?B?B@@@BB@B@D@B@D@B?D@B?D?B@B?D?B?B?B?B?B?D?BAB?D?B?B?B?D?B?D?B@B?D@B?B@B@B@B@B@B@D@B?B@B?D?B@D?B@D?B@D@B?B@D@B?B@D@B?B@B@B@B@BBB@B@BBB@B@BBB@B@@BB?@?BABABCBA@E@CBC?C@C?E?C@C?C?E?C?C?C?C?CAA?CAC?C?C?C?C@C@C@CBABABABABABABADABABABAD?BADABAB?DAB?B?DAB?D?B@B?D@B@@@BB@B@@BB@B@B@D@B?BBB@B@B@@BBBB@@BB@BB@@BBB@@BBB@@@BBB@B@B@B@D?B@B@BBB@B@B@BBB@B@BBB@BBB@B@@@B@BBB@D@B@B@B@B@B@B@BB@@@B?@?BCBA@CBC@ABCBC@ABABC@ABABABC@ABA@AB?B?@@B@@@@?B?@CBA@CBABCBA@CBABABCB@B?@BBB@B@BB@@@BAB?@CBABCBC@ABCBCBA@CBABC@AB?B?B@B@B@D@B@B@B?B?BABA@CBABC@C@C@C@E?C?E?C@C?C@A@A@ABA@ABC@CBC@ABCBCBADCDA", "average_heartrate": 172.0, "average_speed": 2.372, "streak": 3}, {"run_id": 1742689216000, "name": "", "distance": 2295.79, "moving_time": "0:15:17.060000", "type": "Run", "subtype": "", "start_date": "2025-03-23 00:20:16", "start_date_local": "2025-03-23 08:20:16", "location_country": "\u6885\u6eaa\u6e56\u5927\u6865, \u6e58\u6c5f\u65b0\u533a, \u671b\u57ce\u5761\u8857\u9053, \u957f\u6c99\u5e02, \u6e58\u6c5f\u65b0\u533a, \u5cb3\u9e93\u533a, \u957f\u6c99\u5e02, \u6e56\u5357\u7701, 410205, \u4e2d\u56fd", "summary_polyline": "spbkDyrbpTA??C?E?C?CAE?CAE?CAE?CAEAEACAEAEAEACAECEAEAEACAEAEACAEAE?E?EAE?G?E?E?GAE?EAEACAEAEAEAEAE?EAEAC?G?EAE?E?E?E?EAE?CAEACCCCACCCACCCAEACAEACAC?EACAEACACACACAEACACACCCACACCEACACCCCCACCCACCCCCACCCACCCCCCCAACCCACCEACCEACACCEACACAE?EACAE?EAE?CAE?E?C?E?EAC?E?C?EAE?CAEAC?EAE?CAE?CAE?CAE?CAEAEAC?EAE?CAE?E?E?C?E?E?E?C?E@E?E?C@E?C@E@C?C@E@C@E@C@E@C@E@C@C@E@C@E@C@E?C@E@E@E?C@E?E@E?E@C?E?E?C?E?E?C?E?E?C?E?E?C?E?CAE?C?C?EAC?E?CAEACAEACACAEACCCACCEACACAECC?CAEACAE?EACAE?E?EAE?C?E?E?E?C?EAE?CAE?EAC?EAEAC?EACAEACACAEACACCCACACAE?C@ABCBAB?BAD?BAB?BAD?BAB?BADAB?BABAD?BABABAB?BABAB?DAB?BAB?DAB?BAB?D?BAB?B?B?BAD?BAB?BADAB?BABABABADABABABAB?BAB?DAB?B?BAB?DAB?BAB?BAB?D?BAB?B?BAB?BABAB?BAB?BABAB?BABABADA@ABABABADABABABABCBABABABABABABABABABADABABABAD?BABAB?B?B?B?D?BAB?B?D?B?B@B?B@B@B@B@@BB@BB@@BBB@B@BBB?B@D@B@B?B@B@B@@BBB@B@B@D@BBB@D@@BB@BBB@BBB@BBB@B@B@D@B@D@B?B@D@BBB@B@BBB@@BB@B@B@B@B@B@D@B@B?D@B@D?B@B@D?B?B?D?BAD?D?B?B?D?B@B@B?D@B?D?B@D?B?D?B@B?D@B@B?B@D@B@B@B?B@D?B@DAB?DABADABABCBCBABCBABAB?DAB?DAB?D?D?B?D?B@D?B?D?B?D?BAD?BABADABABADCBABADAB?BAD?B?B?D?B?DAB?D?BAD?BAD?BADAB?B?D?B?D?B?B@D?B@D?B?B?B@D?@?@A@?B?B?B@D?D?D?B@D?B@D@B?D@D?B@D?D?B?D@D?D?B@D?B@D?B@D@B@D@B@B@D@B@BBB@BBB@B@BBB@B@D?B@B@D?B?D@D?B?D?D?B?D@B?D@B@D@B?B@DBB@B@B@BBBBB@B@BBB@B@@@BBD@B@B@B?D?B?D?DAD?DAD?D?D?B@D@B@B@B@@BB@BB@BB@BBBBB?D@B?D?D?DAD?D?B?D@B?D@B@B@D@B@@@BB@BBB@B@B@B@B@@B@B@D@B@D?D?F@D?D?B?DAB?B?B?D?B?D@B@B@D@B@BBB@B@DBBBBBB@BBB@BBB@B@B@B@B@B@@BB@BB@@BBB@B@BBB@B@BBB@BBB@B@B@B@B@B@B@D@B@B@B@B@@@BBB@B@B@B@B@D@B@B@D?B@D@B@D?B@D@B@B@D@B@B@D@B?B?BABABCBCBABABAD?B@B@B@B@D@BBB@B@D@BBB@BB@BB@@BBBB@BBB@B@B?D@B@B@B@D@BBB@B@D@B@D@B@B@D@B@B@B@BB@@BB?B@B@B?B@B@BB@B@BBB@B?D@B@BBB@BB@B?B?@ABABAD?B?@@B@@B@B?D@D?B@D?D@B?D?D@B?B@D@B?D@B?D@B@B?D@B@D@B?D@B@D?B@D?B@D@B?B@B?D@B@B@B@D?B@B@D@B@B@D@B@B@B@D@B@B@B@B@D@B?B@D?B?D?BABABCBABC@ABCB?@AB?@?B?@?@@@?B@B", "average_heartrate": 160.0, "average_speed": 2.503, "streak": 1}, {"run_id": 1742817466000, "name": "", "distance": 13139.41, "moving_time": "1:27:29.330000", "type": "Run", "subtype": "", "start_date": "2025-03-24 11:57:46", "start_date_local": "2025-03-24 19:57:46", "location_country": "\u6885\u6eaa\u6e56\u5927\u6865, \u6e58\u6c5f\u65b0\u533a, \u671b\u57ce\u5761\u8857\u9053, \u957f\u6c99\u5e02, \u6e58\u6c5f\u65b0\u533a, \u5cb3\u9e93\u533a, \u957f\u6c99\u5e02, \u6e56\u5357\u7701, 410205, \u4e2d\u56fd", "summary_polyline": "cqbkD{qbpT??AEACCEAEAGCGAECGAEAGAEAE?E?EAC?EAEACAEACAECCAEACCEAEACCEAEAE?GAE?EAG?E?EAG?EAC?EAEAEAEACAEAEAEAE?E?EAE?G?E?E?EAE?EAEACCCCCCCCCCAECEAC?EACACAC?EACCCAEACCCAEACAECCACACCCCCAEACCCACCCACCCACCECCCCCCCCCCCCCAACCACACACCCACAE?EAC?E?EAE?C?EAE?C?E?C?E?E?C?C?E?C?CAC?EACAEACAEAEACAEAE?EAE?EAC?EAE?E?C?EAC?E?C?E?E?E?C?E?E?C?E?E@E?C@E@E@C@E@E@C@EBC@E@C@E@C@E@C?E@E@E?C@E?E@E@C?E@C@E?C@E?E?C?E?E?C?E?C?E?CAE?EAC?E?E?C?E?CAE?EAC?EAEACACACACACCCACAEACACAEACACAEACAEACAE?CAE?C?E?C?C?E?C?E?C@E?C?EAC?EAE?CAEACAEAC?CACAEACCCAEACACCCACACAC?E?C@CBADAB?D?DAF?B?DAB?D?BABADABABADAB?BABAD?BAB?BAD?BAB?B?DAB?BAB?D?B?BAD?B?DAB?BADABABABADABADAB?BADAB?BAD?BAB?DAB?BAB?DAB?D?B?DAB?B?D?BAD?BAB?BADABABCBADABABABABCBABABABCDABABADABABCDABABADABABABADABABABADAB?B?DAB?B?D@B?B?D?B?B?B@D@B@BBBBB@BBBBBBB@B@D@B@B@B?D@B@B@B@BB@B@BBB@D@BBB@BBB@DBB@BBB@B@B@D@B@D@D@BBD@B@B@BBB@BBBBB@DBB@B@B@D@B@D?B@D@B@D@D?D@B?D?DAD?D?B?D?D?B@D?B@D@D?D@D?D?B@D?D@D@B@D@B@D@D@D@B?D?DAD?BADADABCDABCBCDABAD?DADAB?DAD?B?D?D?B?D?D?D?DAD?BADABADABABABABADABABAD?D?B?D?B?B?DAB?BAD?BAD?BAB?DAB?D?B?B?D@B?D@D?B@D@B?D?D?B?D?B?D?B@D?B?D@B@D@B@D?D?D@B?D?B?B@D?B?D@B?D@D?B@D@D@B@DBB@D@B@BBB@B@BBB@B@B@D@D@B@D@D?B@D?B?D?B?D@B?D?D@B?D@B@D?B@BBB@B@BBB@B@BBB@B@B@BBB@B@B@B?B@B@B?B?BAD?D?DAD@D?B?D@D@B@B@BB@@BB@@BBB@B@B@B@D?D@DAD?D?DAB?D?D?B@D@B@D@BBB@BB@B@BBB@BB@@B@@B?B@B?@?B?B?BAB?@?BABAB?D?B?D@D@D@FBDBFBDBDBDBDBBBDBB@@BBB@@B@@@DBB@B@B@B@BBB@B@BBB@B@BBB@B@BBB@B@BBB@B@BBB@B@BBB@B@D@B@B@B@B@BBB@B@B@B@B@B@B@D?B@B@D@B?D@B@B@B@B@D@B@B@B@B?DABADCBA@CBABABAB?B@B@B@B@B@B@B@B@B@B@B@BBB@BB@BB@@BB@B@B@B@B@B@B@BBB@B@DBB@B@D@B@B@D@B@B@B@B@B@B@BBB@BB?B@B@B?B@B@@B@B@B@BBD@B@B@DB@BB@@B@BAB?BABAB?BA@@BB@B@B?D?B@D?D?D@B?D@B?D@B@D?B@B@D?B@D@B@B?D@B?D?B?B@D?B@D@B@B?B@B@D?B@B@B@B@D@B@B@B?BBD@B@B@B@D@B@D@B?B@D@B@B@B@D@B?B?B?DABABCBABA@CB?BAB?B?B?B?BAD?BADCBCBABCBCBCBCBABAB?B?B@D?BBD@DBB@DBBBB@DBB@D@B@D@B@B@D@B@B@D@BBB@BBBBBB@B@B@B?B@B?BAB?BABABABAB?B?@@B@@BBB@BBBBB@D@B@B@B@B@B?B@B?B@D?D?B@D@B?DBB@B@BBB@B@B@B@D@B@D@B?BBD@B@B@DBB@B@B@B@D@B@B@BBD@B@B@DBB@D@B@B@B@B@B@B@B@B@BBB@B@B@B@D@B@BAB?BABCBC@CBCBC@CBC@ABAB?B?B?B@D@B@B@B@BBD@B@B@D@B@D@B@B@B@D@B@B@B@D@B@B@BBD@B@B@D@B@B@B@BBD@B@B@B@BBB@B@@B@B@B@@@B@B@B@@@B@B@B?B?B?BABABA@?BABABCBABA@CBABABCBAB?B?BBB@@BBD?D@B@D@D@B@D@B@B@B@B@B@B@D@B@B@B@BBB@BB@B@B@BAB?DCBABCBABCBABAB?B@B@@BBD@B@D@D@D@B@D@D@B@DBB@D@B@D@B@D@B@B@DBB@B@D@B@D@B@D?D?B?DAD?B?D?D@B?D@D@B@B@D@BBB@B@BBD@BBB@DBD@B@BBD@B@BBD@B@BBD@B@DBD@B@D@B@B@D?B@B@B?D?DADCDCBCBE@EBC@E@C@E@C@C@EBC@ABA@CB?B?D?B?D?D?D?B?D?D@D@B@D?B@D@B?D@B@B@D@B?B@D?D?B?D?D?D@D?D?BAD?DADADCBADADCBADABCDABAB?DABADAD?BAD?D?DAB?D?DAB?DAB?DAB?DABAB?D?DABADADABABCDC@ABCBABAD?BAB?D?B?D?B?D@B?D?B?D?D?BAD?D?D?B?D?D@B@D@B@BB@BBBB@BBBBB@@@BB@B@D?B?B?D?B?B?B?B?BAB?DABAB?BADABABADABABAD?BABABABABABABABABABABABAB?D?B?B?B@D?B@D?D?B?D?B?B?BAD?BABA@?BABABABA@ABABCB?BAD?BAB?D@B?B?B?D?BAB?D?BAB?BADAB?DABABADABAB?BAB?B?@?B@@@@?B@@?B?BABABABABABAB?BABADABABABABABABC@C@CBABAB?B?BBD@BBBBD@BBB@@@B@B?BABABABABC@ADABABCBABABAD?BABAD?BABAB?B?D?B@B?B@B@B@D@BBB@BB@BBB@B@B@B@B@B@B@B@B?D@B@D?D@B@D@B?D@D@B?D@B@B@D@B@BBB@BBB@@BBBBBBB@@BB@B@BBB@B@B@B@B@@@D@B?B@B?B@B@B@B?B@B@B@BBD@B@B@B@D@B@B@B@D@B?D@B?D?B?D?B?B?B?B?D?B@B?B@D?B?B?BAB?BABAB?@@@@?B?B?B?B?B@B@D@B@B@@@B@B@B@@@BBB@B@B@@BB@B?B@D?B@B@D?B@D@B@B@BBB@B@B@@@B@B?D@B?B?D?D?D?B?D?D@B?B@DBB@BB@BBB@BBB@BBB?B@B@B@B@B?B@B@B?B?BA@ABC@C@CBC@CBC@CBA@CBC@C@C@C@CBCBC@CBABCBCBA@AD?B@@@BBBB@@@B@B@D@B?B@B?D?B?B?D?B?D?D?B?D?B?D?B?D?B@D?B?D?B?D@B?D@B@B@D@@@B@@?@@@?@@B?@@D?B?B?D@B?D@B@B?D@B@B?D@B@B?D@B@D@B@B@D@B@D@B@BBB@BB@B@@BBB?B?BA@CBC@ABE@C@C@C@E@C?C@C?C?C?C?EAC?C?E?E?C?E?C?C@C@A@C@ABCBABCBABADABAD?BADABABAD?BABCDAB?BADAB?D@B?B@BBBBBBBB@DBB@D@B@D@B@BBB@BBB@@BB@B@D@BBB@B@BBBBBB@BBB@B@D@B@D@B@D@B@D@BBB@BBBBB@DBB@B@BBB@D@B@B@BBD@B@B@BBB@@@@BA@A@CBABCBABCBABCBCBABC@ABCBABCB@B?B@B@B?B?@CBABABCBC@CBCBABABAB@B@BB@BBB@BB@@?BABABC@CBABCBCBCBC@CDABAB?B?D@B?D@B@B?B@BAB?BABA@CBC@C@C@E?C?E@C?C?C@C@A@A@CBCBA@CBC@CBCBABCBABABABA@CBABC@C@C@C@E?C@E?C@E?C?E?E?C?EAE?C@E@C@CBCBCBABAB?B?B?D?B@D?B?B@D?B@B@B?B@D@B@B@B@B@B@B@BBB@B@B@BBB@B@D@B@B@D@B@B@B@BB?B@D?BADADAB?D?B?B@B@B@B@D@B@D@B?D@D?B?D?B@B?D?D?B?D?B?D@D?B@D?D@B@D@B@D@D@B@D@B@D?B@D@B@DBB@D@B@D?B@D@D@B?D@B?D@D@D?B@D@D?D@B?D@D?D@B?D@D?D@D?D?B@D?D?B?D?D@D?D?B?D?D?BAD?B?D?D?BAD?D?D?B?D?B?D?BAD?D?B?D?B?DAB?D?D?B?D?BAD?D?BADAB?DABAD?DADAB?DABAD?DADABADABADAB?DABADABADABADAB?DABADABABADABABABABADABABABCDABC@ABABCDABABABABADABCBABCBABC@ABCBCBABABCBABABABCBCBABABAB?B?B?B?B@@?B@@?B?B@B?B?B@B?BAB?BAB?BABAB?BABADA@?BABA@AB?@ABA@A@ABA@CBA@CBABC@CBABABABCBABABABADABAB?DABABADABABABADCBABABABADABCBABABABCBABC@ABCBCBABC@ABCBC@CBA@CBABABAB?D@B@B?D@B@D?B?DABADABCBABC@CBCBA@C@CBC@ABCBA@CB?BAB?BAD?B?D?B?D?BABADABABABCBABC@CBABC@C@C@C@C@E@C?C@E?C@C@C?C@CBC@C@CBABCBAD?BAD?B@D?D@B@DBB@DBB@@BBB@B@B@B@D@@@BBB@BBBBB@BB@BBB@B@B@B@B@D@B@B@B?D@B?DABAD?BABAD?B?B?D@B@B?D?B?DABABCBC@C@CBE@A@C@CBC@CBABC@CBCBABC@ABCBABABC@ABCBC@A@C@C@C@C@A@C@C@C@C@E@C@C@C@E@C?C@C@C@C@C@C?C@C@C@C@C@C?C@C@C@C@C?C@E@C@E@C?C@E@C@C@C?C@C@C?C@C?C@E?C@E?C@E?E@C?E@C@E?C@C?C@E@C?C@E@C?C?C?C@C@C?C@C?C@E?C?EAC?C?EAC?C@E?C?C@E?C@C?C?C?C?C?CAC?CAC?C?CAE?C?C?E?CAE?CAC?CCCACCCACCACCCACCCCACCACCACCAAACACACAC?E?EAE?C?E?E@C?E?C?E?C?E?E?C?E@E?C?E?EAC?E?C?E?E?CAE?CAC?CCAACAACACACCC?CAC?C?CAE?C?CAC?EAC?E?CAEAC?EAC?CAC?CAC?E?CAC?EAC?CAEAC?EAC?CAC?CAA?C?C@C?C@C@C@C@CBABA@CBABABABADABADADAD?BADAB?DADABADABADABCBABABABABABABABABAB?BA@ADABABC@CBC@C?C?E?CAEACACCEACCCACACACCCACCCACCCACCCACCCACCCACACCCACACACCAACACCCCCACACCCACACCAACCCACACAACCACACCCAACCACAACCCACAACCACAACCACCCCACACACAAACCCACACCCACCACCACCACCACCACCAACCCCAACCAACCCCAACCCACACACCCAACCACCAACCCCCACCCCCACCCACCCACCCCEACCCACACCCACAECCACCCACACCCACAEACACACAEACCCACAEACCCACAEACCCAEACACAECCACACACACAEACACCCACACAEACACAECCACAEAEAC?EACACAEACACACAEACAEAC?EACACACAEACACAE?CAEACAEAC?CAEACACAEAC?EACAEACAEACAE?CAEACACACAEACACACAE?CAC?E?C?E?CAE?CAE?EACAEAEACAEACAEACAC?EACACAEACACAEACACCCAEACAC?CACAEAC?CACACACACACAEACAEAC?EAEAC?EAE?CAE?EAC?EAE?CAE?EAC?EACAEACACACACACAC?CAC?E?E?CAE?EAE?EAC?EACAEAC?CAEAEACAEAC?EACAE?CAC?EAC?EACAC?EACAEAEACAEACAEAEACAC?CAE?CACAEACAEAEACAEAC?EACAEACACAEACACAAACAACAACAACCAC?CAE?CAE?C?E@CAE?E?CAEAC?CACAE?CAC?CAE?CAC?CAE?CAEACAE?EACAEAEACAEAEAEACAEACAC?CAEAC?CACACACAEACAE?EACAEACACAEACAC?EACACAC?CAE?CAA?CAC?CACAEAC?CAEACAEACAE?CAE?CACAEAC?CAEACACAEAC?EACACAEACAC?EACACAE?CACAE?CAEACAE?CACAE?CACAC?CAE?CAC?EAC?EACAC?EACAEAC?E?CAC?E?CAC?EAC?EAC?CAE?CACACAEAAACACCCACACACACACACACAEACACACACACAE?CACACAEACACACACACACACACACACACACACAC?EAEAC?E?EACAE?CACACAEACACACAEACACCEACCCACCCACCCCCACCCACACCCACACCCACACCEACACCCACCCACCACCCCCCCCACCCACCCACCCCCACCACCACCCCACCACCACCAACCACAC?E?CACACACAAACCACACAAACACCCAACCACCACEACCCAACCACACCCACCCAAACCCACCCAACECCACCCCAACCCACACCCACACACACAEACCCACACACAAACACCCACACACCCACACCAAAACAAACAC?A?CAA?C?CACAACCCCACCACCCCCCACCCCCCCACCACCACCAACCCACAACCACCAACCCCCCCACCACCCCCACCCCAACCCCAACCCACACACCCACACCCAACCCCACCCACCCACACCCACCAACACCCACCCACCCACACCCACAEACCCACACCCAEACACACCEACACAECCACACACCCACAECCACACAEAC?EAC?EACAE?CACACACACACACACAE?CACACAEACACAAAC?CACACAC?CACACAEAEACCEAEACACAEACACACAEACACACAEACAEACAC?CACAEACAC?EAC?EAE?C?E?C?CAE?C?E?C?E?C@E?E?C@E?E@C?E?E?C?EAE?C?E?CAC?E?CAE?CAEACACACACCCACAEACACCEAC?CAEAC?EACAE?CAE?CAE?E?CAE?E?E?C?E@C?E@E?C@E@E@C@E@C?E@C?E?E?C?E?C?EAC?E?C?C?E?C?E?C?EAC?C?C?A?C?CAC?C?C?EACACACACAAACAAACAC?C?C?CAC?C?E?C?C?EAC?C?E?C?CAE?C?C?C?C?E?C@C?E?C?C@C?E?A?C?C?C?C?C?C?C@C@E@C@EBC@CBCBC@ABC@ABA?C@A@C?C?C?E?E?C?E?E?C?E?E?C?C?EAC?EAC?CAE?CACAC?EACACAEACACAE?CAE?C?E?EAC?E?EACAE?C?EAC?E?E?CAC?E?CAC?C?E?C@C@E@C?E@E@C@E?E@C?E@E?C@E?E?C@E?E?CAE?C?E?CAE?C?EAC?EAC?EAE?CACAE?CAEACACAE?CAEACAEAC?EACAC?EACACAEACAEAC?EACAE?EACAE?CAE?E?C?E?EAC?E?CAE?CAEAE?CAEACAE?CAC?E?E?C?E?C?E?CAE?CAE?CAE?C?EAE?C?E?C?EAE?CAE?EAC?EAE?C?E?E?C?E?C?E@C?E?C@E?C@E?C?EAC?E?CAC?EAC?CAC?EAE?GAE?GAE?GAE?CAE?CAE?CAE?CAEAC?EACAE?CACAEACACCCACACAEAC?CAEACAE?EAC?E?CAE?E?E?CAE?E?EAC?EAEACAE?CACACACAC?C?EAC?EAC?EAE?EAE?E?E?C?C?EAA?CAAAAACAACACACAAAEAC?CAC?EACACAC?CACAECCACACACACCCACAC?CACACACACAACCACCCCACCAACCACCAACACCCCCAACAEACACCCACACAEACACACAE?CACACAEACACAE?C?E?E?C?E?C?E?CAC?EACAC?EACAE?CAE?C?EAC?E?CAEAC?EAC?EAC?EACAE?EAC?E?C?E@C?C?E?C?E@C?C@E?C?E@C?E@C?E@C@C@C@E@C@C@C@C@C@C@E@C@C?C@E@C?C@E?C@C?E@C?E?E@C?E?C?E@C?C?EAC?C?E?C?E?C?CAE?C?E?C?EAC?E?C?EAC?C?CACACACACACACAAACACCCACACACACAC?CAEACAC?CAE?CAC?EAC?E?C?E?C?E?CAE?C?E?CAC?E?CACAE?CACACAE?CACACCCACAEACACCC?CAA@C@CBABABAD?BADABAD?BADAB?BADAB?DAB?BABAD?BABAB?BAD?BAB?DAB?DAB?B?DAB?BAD?B?BAD?BABABAD?BABAB?BABADABABABAD?BABAD?BAB?DAB?DAB?BAB?DAB?B?D?B?BAB?BABAB?DABABABABABABABABABCBABABABABADCBABABABABABADABABABCDAB?BABAD?BABAB?BAB?B?B?B?B?B@D?B?B@B@B?B@B@BBB@BBB@@BBBB@B@BBB@B@B?B?B@B?B@B@@BBB@D@BBB@D@B@BBB@B@BBB@BB@@B@B@B?D@B@B?D@B@B?BBB@B@@BB@BBBBBBB@BBB@D@B@D?B@D@D@B?B@D@B@D?B?DAD?DAB?DAD?B?B@D?B@D@B?D@B?D@D?B?D@B?D@B@B@B@D@B@B@B@B?D?B?D?BAD?DABADCBABABCBABABADABAB?BAD?B?B?D?B?D@B?D?D?DAB?DADABADABADABABADABAB?DAB?D?B?BAB?D?D?BADAB?DABAD?B?BAD?B?B?B?D?B?B@B?D@B?B?D@B?B?D?B?B@B?D?B?B@D?B?B@D@B?B@D?B?D@B?D?B?D@B?B?D@B?D@B@D?B@D@B@D?B@BBD@B@BBBBB@B@BBB@B@D@B?D@B?D?B@D?B?D?B@D?B?D@B?D@B@D@B@D@B@BBB@B@B@BB@@B@B@B@B@B@B@B@@?B@D?B@B?B?D?D?B?D?D?D?B@D?B@D@B@B@B@BB@@BBB@@BB@BBD?B@D?D?D?BAD?B@D?B?D?B@B?B@B@B@BB@BBB@B@B@B@B@B@@B@@?B@@?D?B?BAD?B?B?D?B?D?B@D?D@D@D@D@BBD@D@BBDBB@DBB@BBB@BBB@@@BBB@B@BBD@B@B@BBB@B@B@B@B@@@B@BBB@B@B@BBB@B@B@BBB@B@B@B@BBB@D@B@B@B@D@B@BBB@B@B?B@B@D?B@B@D?B@B@D@B@B?BBD@B?B?BABABCBABABADAB?B?B@B@B@B@B@B@B@B@B@B@BBBB@@@BBB@@B@@@B@B?D@B@B@B@B@B@B@BBB@B?B@B@D@B@B@B@B?D@B@B@BBB@B@@@@B?B?B?@?B?B@@@BD@B@B@D@B?B@B@BBB@BB@B?BAB?BADA@AB?B?@@@@?B@B?D@B?D@D?D@B@D?B@D?B@B?B@D?B@B@D?B@D@D@D?D@B?D@D@B?D@B@D?B@B@B?B@D@B@B?B@B@B@D@B@D@B@D@B@D@B@B@B@D@B@B@B@D?B@B?B@DABABCBA@ABAB?BAB?D@B?B@D?B?BABADABABC@CBCBCBABCBAB?D?B?B?D@B?B@B@D@BBB@D@B@D@B@D@B@B@B@B@B@B@D@B@@BBB@@@DAB?D?BAD?DAB?BAD@B?B?B@@BB@@BBD@B@BBD@B@D@B@B@D@B@B@B@D@B@B?D@B@B@D@B@B@D@B@B@BBB@B@B@D@B@D@BBB@D@B@D@B@B@D@B@B@B@B@D@B@BBB@D@B@B@B@B@D@B@B@B@B@B@D@B@DBB@B?D?BABABCBC@CBCBC@EBA@CB?BAB@B?B@B@D@B@B@BBB@B@B@B@B@B@B@B@@@D@BBB@B@D@B@B@B@B@B@B@B@B@BBB@B@B@B@BBD@B@B@B@B@B@BB@@BB@BB@@B@B@D?B@B?B?B?BABABABABABABCBA@ABCBA@ABABCB?B?@BB@@B@DBB@B@D@B@BBB?D@B@B@B@B@B?D@B@B@B@B@DB@@B@@B@B?BAB?BABCBA@C@C@C?CAEACCAACCACCCACACAAACACCAACCACACACACACACAEACAEACAEACACACACACAACAA?A@C@CBCBCBC@CBC@C@C@C@C?C?AACAAACAC?A@C@C@C@A@CBC@C@C@C@C@C?C?CAACCCACAEACAEACACAEACACACAEACACACCC?EACACAEACACACACACACACAEACACACACAEACACACAC?E?C?C@C@CBCBABABCBABABC@A@C?CAC?ACEACACACCCACACACAEACACAEACCEAEACAEACCEACACCEACACAECCAEACACACACCEACACACACAEACACACCEACACACACACAEACACACAEACAACAA?A@A@A@CBC@ABC@CBC@CBC@C@C@C@C@C@A@C@CBC@C@C@C@C@C@ABC@C@C@CBA@C@C@C@CBA@C@C@C@A@C@C@C@C@C@C@C@A@C@C@C@E@C@C?C?C@C@C?C@C@E?C@C?E?C@C?E?C@C?C?C?C?E@C?C@C?E@C?C@C?C@C?C@C?C@C?E?C@C?C?C@C?E?C@C?C@C?G@", "average_heartrate": 160.0, "average_speed": 2.503, "streak": 2}]